openct/__init__.py
openct/__main__.py
openct/connections/__init__.py
openct/connections/connections.py
openct/datastore/__init__.py
openct/datastore/datastore.py
openct/devices/__init__.py
openct/devices/devices.py
openct/setup/__init__.py
openct/setup/__main__.py
openct/setup/config.py
openct/setup/config_schema.py
openct/setup/setup.py
openct-0.1.8.dist-info/LICENSE
openct-0.1.8.dist-info/METADATA
openct-0.1.8.dist-info/WHEEL
openct-0.1.8.dist-info/entry_points.txt
openct-0.1.8.dist-info/RECORD
