Metadata-Version: 2.1
Name: openct
Version: 0.1.8
Summary: Configuration backup and analysis tools for devices running pfSense and RouterOS
Home-page: https://github.com/weehooey/openct
License: GNU GPL v3.0
Author: Weehooey
Author-email: info@weehooey.com
Requires-Python: >=3.11,<4.0
Classifier: License :: Other/Proprietary License
Classifier: Programming Language :: Python :: 3
Classifier: Programming Language :: Python :: 3.11
Requires-Dist: PyYAML (>=6.0,<7.0)
Requires-Dist: fabric (>=3.1.0,<4.0.0)
Requires-Dist: tqdm (>=4.65.0,<5.0.0)
Project-URL: Repository, https://github.com/weehooey/openct
